public_suffix_list/__init__.py
public_suffix_list/psl.py
public_suffix_list/py.typed
public_suffix_list-1.1.0.dist-info/LICENSE
public_suffix_list-1.1.0.dist-info/METADATA
public_suffix_list-1.1.0.dist-info/WHEEL
public_suffix_list-1.1.0.dist-info/top_level.txt
public_suffix_list-1.1.0.dist-info/RECORD
