Metadata-Version: 2.1
Name: public-suffix-list
Version: 1.1.0
Summary: Split domain names into subdomain, registered, and public parts per the Public Suffix List
Home-page: https://github.com/plinss/public_suffix_list/
Author: Peter Linss
Author-email: pypi@linss.com
License: UNKNOWN
Platform: UNKNOWN
Classifier: Programming Language :: Python :: 3
Classifier: License :: OSI Approved :: MIT License
Classifier: Operating System :: OS Independent
Requires-Python: >=3.6
Requires-Dist: idna
Requires-Dist: typing-extensions
Provides-Extra: dev
Requires-Dist: mypy ; extra == 'dev'
Requires-Dist: flake8 ; extra == 'dev'
Requires-Dist: flake8-import-order ; extra == 'dev'
Requires-Dist: flake8-annotations ; extra == 'dev'
Requires-Dist: flake8-type-annotations ; extra == 'dev'
Requires-Dist: flake8-docstrings ; extra == 'dev'
Requires-Dist: pep8-naming ; extra == 'dev'
